setup.py
pullback_exp_sar_forex_next3/__init__.py
pullback_exp_sar_forex_next3/pullback_exp_sar_forex_next3.py
pullback_exp_sar_forex_next3.egg-info/PKG-INFO
pullback_exp_sar_forex_next3.egg-info/SOURCES.txt
pullback_exp_sar_forex_next3.egg-info/dependency_links.txt
pullback_exp_sar_forex_next3.egg-info/not-zip-safe
pullback_exp_sar_forex_next3.egg-info/top_level.txt