Metadata-Version: 1.0
Name: pullback-exp-sar-forex-next3
Version: 1.9
Summary: pullback_exp_sar_forex_next3
Home-page: UNKNOWN
Author: omid
Author-email: UNKNOWN
License: UNKNOWN
Platform: UNKNOWN
